AUTHORS.rst
CONTRIBUTORS.md
LICENSE
MANIFEST.in
README.md
requirements.txt
setup.py
tox.ini
climetlab_wekeo_mercator/__init__.py
climetlab_wekeo_mercator/arctic_analysis_forecast_phys.py
climetlab_wekeo_mercator/arctic_analysis_forecast_wav.py
climetlab_wekeo_mercator/arctic_analysisforecast_bgc.py
climetlab_wekeo_mercator/arctic_analysisforecast_phy_ice.py
climetlab_wekeo_mercator/arctic_analysisforecast_phy_tide.py
climetlab_wekeo_mercator/arctic_multiyear_bgc.py
climetlab_wekeo_mercator/arctic_multiyear_phy.py
climetlab_wekeo_mercator/arctic_multiyear_wav.py
climetlab_wekeo_mercator/balticsea_analysisforecast_bgc.py
climetlab_wekeo_mercator/balticsea_analysisforecast_phy.py
climetlab_wekeo_mercator/balticsea_analysisforecast_wav.py
climetlab_wekeo_mercator/balticsea_multiyear_bgc.py
climetlab_wekeo_mercator/balticsea_multiyear_phy.py
climetlab_wekeo_mercator/balticsea_reanalysis_wav.py
climetlab_wekeo_mercator/blksea_analysisforecast_bgc.py
climetlab_wekeo_mercator/blksea_analysisforecast_phy.py
climetlab_wekeo_mercator/blksea_analysisforecast_wav.py
climetlab_wekeo_mercator/blksea_multiyear_phy.py
climetlab_wekeo_mercator/blksea_multiyear_wav.py
climetlab_wekeo_mercator/blksea_reanalysis_bio.py
climetlab_wekeo_mercator/global_analysis_forecast_bio.py
climetlab_wekeo_mercator/global_analysisforecast_phy.py
climetlab_wekeo_mercator/global_analysisforecast_wav.py
climetlab_wekeo_mercator/global_multiyear_bgc.py
climetlab_wekeo_mercator/global_multiyear_phy.py
climetlab_wekeo_mercator/global_multiyear_wav.py
climetlab_wekeo_mercator/global_reanalysis_phy.py
climetlab_wekeo_mercator/ibi_analysis_forecast_wav.py
climetlab_wekeo_mercator/ibi_analysisforecast_bgc.py
climetlab_wekeo_mercator/ibi_analysisforecast_phy.py
climetlab_wekeo_mercator/ibi_multiyear_bgc.py
climetlab_wekeo_mercator/ibi_multiyear_phy.py
climetlab_wekeo_mercator/ibi_multiyear_wav.py
climetlab_wekeo_mercator/insitu_arc_phybgcwav_discrete_mynrt.py
climetlab_wekeo_mercator.egg-info/PKG-INFO
climetlab_wekeo_mercator.egg-info/SOURCES.txt
climetlab_wekeo_mercator.egg-info/dependency_links.txt
climetlab_wekeo_mercator.egg-info/entry_points.txt
climetlab_wekeo_mercator.egg-info/requires.txt
climetlab_wekeo_mercator.egg-info/top_level.txt
climetlab_wekeo_mercator.egg-info/zip-safe
